mistral/context.py
mistral/config.py
mistral/expressions.py
mistral/__init__.py
mistral/exceptions.py
mistral/yaql_utils.py
mistral/version.py
mistral/db/__init__.py
mistral/db/sqlalchemy/types.py
mistral/db/sqlalchemy/base.py
mistral/db/sqlalchemy/__init__.py
mistral/db/sqlalchemy/model_base.py
mistral/db/sqlalchemy/sqlite_lock.py
mistral/db/sqlalchemy/migration/cli.py
mistral/db/sqlalchemy/migration/__init__.py
mistral/db/sqlalchemy/migration/alembic.ini
mistral/db/sqlalchemy/migration/alembic_migrations/script.py.mako
mistral/db/sqlalchemy/migration/alembic_migrations/__init__.py
mistral/db/sqlalchemy/migration/alembic_migrations/README.md
mistral/db/sqlalchemy/migration/alembic_migrations/env.py
mistral/db/sqlalchemy/migration/alembic_migrations/versions/001_kilo.py
mistral/db/sqlalchemy/migration/alembic_migrations/versions/002_kilo.py
mistral/db/sqlalchemy/migration/alembic_migrations/versions/__init__.py
mistral/db/v2/__init__.py
mistral/db/v2/api.py
mistral/db/v2/sqlalchemy/models.py
mistral/db/v2/sqlalchemy/__init__.py
mistral/db/v2/sqlalchemy/api.py
mistral/workflow/direct_workflow.py
mistral/workflow/with_items.py
mistral/workflow/base.py
mistral/workflow/data_flow.py
mistral/workflow/states.py
mistral/workflow/__init__.py
mistral/workflow/reverse_workflow.py
mistral/workflow/commands.py
mistral/workflow/utils.py
mistral/utils/rest_utils.py
mistral/utils/ssh_utils.py
mistral/utils/__init__.py
mistral/utils/serializers.py
mistral/utils/wf_trace.py
mistral/utils/javascript.py
mistral/utils/inspect_utils.py
mistral/utils/openstack/keystone.py
mistral/utils/openstack/__init__.py
mistral/cmd/launch.py
mistral/cmd/__init__.py
mistral/services/action_manager.py
mistral/services/periodic.py
mistral/services/triggers.py
mistral/services/workflows.py
mistral/services/actions.py
mistral/services/workbooks.py
mistral/services/__init__.py
mistral/services/security.py
mistral/services/scheduler.py
mistral-2015.1.0.dist-info/WHEEL
mistral-2015.1.0.dist-info/metadata.json
mistral-2015.1.0.dist-info/entry_points.txt
mistral-2015.1.0.dist-info/METADATA
mistral-2015.1.0.dist-info/RECORD
mistral-2015.1.0.dist-info/DESCRIPTION.rst
mistral-2015.1.0.dist-info/pbr.json
mistral-2015.1.0.dist-info/top_level.txt
