Metadata-Version: 2.0
Name: mistral
Version: 2015.1.0
Summary: Mistral Project
Home-page: https://launchpad.net/mistral
Author: Openstack Mistral Team
Author-email: openstack-dev@lists.openstack.org
License: Apache License, Version 2.0
Platform: UNKNOWN
Requires-Dist: alembic (>=0.7.2)
Requires-Dist: amqplib (>=0.6.1)
Requires-Dist: argparse
Requires-Dist: Babel (>=1.3)
Requires-Dist: croniter (>=0.3.4)
Requires-Dist: eventlet (>=0.16.1,!=0.17.0)
Requires-Dist: iso8601 (>=0.1.9)
Requires-Dist: jsonschema (>=2.0.0,<3.0.0)
Requires-Dist: keystonemiddleware (>=1.5.0,<1.6.0)
Requires-Dist: kombu (>=2.5.0)
Requires-Dist: mock (>=1.0)
Requires-Dist: networkx (>=1.8)
Requires-Dist: oslo.config (>=1.9.3,<1.10.0)
Requires-Dist: oslo.db (>=1.7.0,<1.8.0)
Requires-Dist: oslo.messaging (>=1.8.0,<1.9.0)
Requires-Dist: oslo.utils (>=1.4.0,<1.5.0)
Requires-Dist: paramiko (>=1.13.0)
Requires-Dist: pbr (>=0.6,!=0.7,<1.0)
Requires-Dist: pecan (>=0.8.0)
Requires-Dist: posix-ipc
Requires-Dist: python-cinderclient (>=1.1.0,<1.2.0)
Requires-Dist: python-glanceclient (>=0.15.0,<0.18.0)
Requires-Dist: python-heatclient (>=0.3.0,<0.5.0)
Requires-Dist: python-keystoneclient (>=1.1.0,<1.4.0)
Requires-Dist: python-neutronclient (>=2.3.11,<2.5.0)
Requires-Dist: python-novaclient (>=2.22.0,<2.24.0)
Requires-Dist: PyYAML (>=3.1.0)
Requires-Dist: requests (>=2.2.0,!=2.4.0)
Requires-Dist: six (>=1.9.0)
Requires-Dist: SQLAlchemy (>=0.9.7,<=0.9.99)
Requires-Dist: stevedore (>=1.3.0,<1.4.0)
Requires-Dist: WSME (>=0.6)
Requires-Dist: yaql (==0.2.6)
